{
  "version": "2.0",
  "last_updated": "2024-01-15",
  "description": "抢课增强版 v2.2 授权文件",
  "licenses": [
    {
      "user_id": "2022150404",
      "username": "用户2022150404",
      "license_key": "ABC123DEF456GHI789JKL",
      "expire_date": "2026-12-31",
      "features": ["basic", "premium", "auto_cookie"],
      "status": "active",
      "max_machines": 2,
      "created_at": "2024-01-15",
      "note": "抢课增强版授权用户"
    },
    {
      "user_id": "2022153623",
      "username": "用户2022153623", 
      "license_key": "XYZ789ABC123DEF456GHI",
      "expire_date": "2026-12-31",
      "features": ["basic", "premium", "auto_cookie"],
      "status": "active",
      "max_machines": 2,
      "created_at": "2024-01-15",
      "note": "抢课增强版授权用户"
    },
    {
      "user_id": "2022152155",
      "username": "用户2022152155",
      "license_key": "MNO456PQR789STU123VWX",
      "expire_date": "2026-12-31", 
      "features": ["basic", "premium", "auto_cookie"],
      "status": "active",
      "max_machines": 2,
      "created_at": "2024-01-15",
      "note": "抢课增强版授权用户"
    },
    {
      "user_id": "2022152117",
      "username": "用户2022152117",
      "license_key": "DEF456GHI789JKL123MNO",
      "expire_date": "2026-12-31",
      "features": ["basic", "premium", "auto_cookie"], 
      "status": "active",
      "max_machines": 2,
      "created_at": "2024-01-15",
      "note": "抢课增强版授权用户"
    },
    {
      "user_id": "2022152742",
      "username": "用户2022152742",
      "license_key": "PQR789STU123VWX456YZA",
      "expire_date": "2026-12-31",
      "features": ["basic", "premium", "auto_cookie"],
      "status": "active", 
      "max_machines": 2,
      "created_at": "2024-01-15",
      "note": "抢课增强版授权用户"
    },
    {
      "user_id": "2023152443",
      "username": "用户2023152443",
      "license_key": "GHI789JKL123MNO456PQR",
      "expire_date": "2026-12-31",
      "features": ["basic", "premium", "auto_cookie"],
      "status": "active",
      "max_machines": 2,
      "created_at": "2024-01-15", 
      "note": "抢课增强版授权用户"
    }
  ],
  "features_description": {
    "basic": "基础抢课功能",
    "premium": "高级功能（智能重试、错误统计等）",
    "auto_cookie": "自动获取Cookie功能"
  },
  "license_info": {
    "total_users": 6,
    "active_users": 6,
    "expired_users": 0,
    "disabled_users": 0
  }
}
